chess_transformer/__init__.py
chess_transformer/__init__.pyi
chess_transformer/metrics.py
chess_transformer/fen/__init__.py
chess_transformer/fen/__init__.pyi
chess_transformer/fen/_labels.py
chess_transformer/fen/_metrics.py
chess_transformer/fen/samples.py
chess_transformer/multi/__init__.py
chess_transformer/multi/__init__.pyi
chess_transformer/multi/samples.py
chess_transformer/pytorch/__init__.py
chess_transformer/pytorch/__init__.pyi
chess_transformer/pytorch/_decode.py
chess_transformer/pytorch/_loss.py
chess_transformer/pytorch/_masking.py
chess_transformer/pytorch/metrics.py
chess_transformer/pytorch/fen/__init__.py
chess_transformer/pytorch/fen/__init__.pyi
chess_transformer/pytorch/fen/_metrics.py
chess_transformer/pytorch/fen/samples.py
chess_transformer/pytorch/models/__init__.py
chess_transformer/pytorch/models/chessbert.py
chess_transformer/pytorch/models/gpt.py
chess_transformer/pytorch/models/rnn.py
chess_transformer/pytorch/models/t5.py
chess_transformer/pytorch/multi/__init__.py
chess_transformer/pytorch/multi/_metrics.py
chess_transformer/pytorch/multi/samples.py
chess_transformer/pytorch/uci/__init__.py
chess_transformer/pytorch/uci/__init__.pyi
chess_transformer/pytorch/uci/_metrics.py
chess_transformer/pytorch/uci/decode.py
chess_transformer/pytorch/uci/samples.py
chess_transformer/uci/__init__.py
chess_transformer/uci/__init__.pyi
chess_transformer/uci/_decode.py
chess_transformer/uci/_labels.py
chess_transformer/uci/_metrics.py
chess_transformer/uci/samples.py
chess_transformer/viz/__init__.py
chess_transformer/viz/__init__.pyi
chess_transformer/viz/diff.py
chess_transformer/viz/tensors.py
chess_transformer/vocab/__init__.py
chess_transformer/vocab/sans.py
chess_transformer/vocab/vocab.py
chess_transformer-0.1.41.dist-info/METADATA
chess_transformer-0.1.41.dist-info/WHEEL
chess_transformer-0.1.41.dist-info/top_level.txt
chess_transformer-0.1.41.dist-info/RECORD
